jaxace/Artifacts.toml
jaxace/__init__.py
jaxace/background.py
jaxace/core.py
jaxace/initialization.py
jaxace/utils.py
jaxace-0.4.1.dist-info/LICENSE
jaxace-0.4.1.dist-info/METADATA
jaxace-0.4.1.dist-info/WHEEL
jaxace-0.4.1.dist-info/entry_points.txt
jaxace-0.4.1.dist-info/RECORD
