Metadata-Version: 2.3
Name: jaxace
Version: 0.4.1
Summary: JAX implementation of AbstractCosmologicalEmulators.jl interface with artifact support
Author: marcobonici
Author-email: bonici.marco@gmail.com
Requires-Python: >=3.10,<4.0
Classifier: Programming Language :: Python :: 3
Classifier: Programming Language :: Python :: 3.10
Classifier: Programming Language :: Python :: 3.11
Classifier: Programming Language :: Python :: 3.12
Classifier: Programming Language :: Python :: 3.13
Requires-Dist: diffrax (>=0.7.0,<0.8.0)
Requires-Dist: fetch-artifacts (>=0.1.0,<0.2.0)
Requires-Dist: flax (>=0.10.0,<0.11.0)
Requires-Dist: interpax (>=0.3.9,<0.4.0)
Requires-Dist: jax (>=0.4.30)
Requires-Dist: numpy (>=2.2.6,<3.0.0)
Requires-Dist: quadax (>=0.2.9,<0.3.0)
